audiox/__init__.py
audiox/extract_audio.py
audiox-1.0.0.dist-info/licenses/LICENSE.txt
tests/__init__.py
tests/test_extract_audio.py
audiox-1.0.0.dist-info/METADATA
audiox-1.0.0.dist-info/WHEEL
audiox-1.0.0.dist-info/top_level.txt
audiox-1.0.0.dist-info/RECORD
